bpnet_lite-1.0.0.data/scripts/bpnet
bpnet_lite-1.0.0.dist-info/licenses/LICENSE
bpnetlite/__init__.py
bpnetlite/attribute.py
bpnetlite/bpnet.py
bpnetlite/chrombpnet.py
bpnetlite/io.py
bpnetlite/logging.py
bpnetlite/losses.py
bpnetlite/marginalize.py
bpnetlite/performance.py
bpnet_lite-1.0.0.dist-info/METADATA
bpnet_lite-1.0.0.dist-info/WHEEL
bpnet_lite-1.0.0.dist-info/top_level.txt
bpnet_lite-1.0.0.dist-info/RECORD
